{
    "items": [
        {
            "id": "1",
            "name": "돈까스",
            "category_id": "4",
            "price": "8000",
            "date": "2024-06-10",
            "memo": ""
        },
        {
            "id": "23",
            "name": "버스",
            "category_id": "5",
            "price": "5000",
            "date": "2024-06-10",
            "memo": ""
        },
        {
            "id": "33",
            "name": "월급",
            "category_id": "1",
            "price": "100000",
            "date": "2024-06-10",
            "memo": ""
        },
        {
            "id": "43",
            "name": "용돈",
            "category_id": "2",
            "price": "50000",
            "date": "2024-06-10",
            "memo": ""
        }
    ],
    "profile": [
        {
            "name": "",
            "email": ""
        }
    ],
    "category": [
        {
            "id": "1",
            "title": "월급",
            "type": "income"
        },
        {
            "id": "2",
            "title": "용돈",
            "type": "income"
        },
        {
            "id": "3",
            "title": "기타",
            "type": "income"
        },
        {
            "id": "4",
            "title": "식비",
            "type": "outcome"
        },
        {
            "id": "5",
            "title": "교통",
            "type": "outcome"
        },
        {
            "id": "6",
            "title": "쇼핑",
            "type": "outcome"
        },
        {
            "id": "7",
            "title": "의료",
            "type": "outcome"
        },
        {
            "id": "8",
            "title": "기타",
            "type": "outcome"
        }
    ]
}
